pyocli-0.1.0.dist-info/METADATA
pyocli-0.1.0.dist-info/WHEEL
pyocli.libs/libcrypto-b3b4e4c6.so.3
pyocli.libs/libssl-fa628c97.so.3
pyocli.libs/libzstd-27f07c9a.so.1
pyocli/__init__.py
pyocli/pyocli.abi3.so
pyocli-0.1.0.dist-info/RECORD
